CHANGELOG.md
LICENSE.txt
MANIFEST.in
README.md
requirements.txt
setup.py
django_react/__init__.py
django_react/bundle.py
django_react/conf.py
django_react/exceptions.py
django_react/models.py
django_react/render.py
django_react/templates.py
django_react.egg-info/PKG-INFO
django_react.egg-info/SOURCES.txt
django_react.egg-info/dependency_links.txt
django_react.egg-info/requires.txt
django_react.egg-info/top_level.txt
django_react/services/__init__.py
django_react/services/package.json
django_react/services/render.js