Metadata-Version: 1.0
Name: django-react
Version: 0.11.1
Summary: Render and bundle React components from a Django application
Home-page: https://github.com/markfinger/django-react
Author: Mark Finger
Author-email: markfinger@gmail.com
License: UNKNOWN
Platform: UNKNOWN
